FancyLogger/__init__.py
FancyLogger/commands/__init__.py
FancyLogger/processing/__init__.py
FancyLogger-1.1.0.dist-info/DESCRIPTION.rst
FancyLogger-1.1.0.dist-info/METADATA
FancyLogger-1.1.0.dist-info/RECORD
FancyLogger-1.1.0.dist-info/WHEEL
FancyLogger-1.1.0.dist-info/metadata.json
FancyLogger-1.1.0.dist-info/top_level.txt
