Metadata-Version: 2.0
Name: FancyLogger
Version: 1.1.0
Summary: Fork of aubricus/print_progress.py originated from StackOverflow's Greenstick to allow using multiple progress bars along with regular message logger.
Home-page: https://github.com/peepall/FancyLogger
Author: peepall
Author-email: ms.acc.783@gmail.com
License: MIT
Keywords: logging progress bar debug logger info task multiprocess
Platform: UNKNOWN
Classifier: Development Status :: 4 - Beta
Classifier: Intended Audience :: Developers
Classifier: Topic :: System :: Logging
Classifier: License :: OSI Approved :: MIT License
Classifier: Programming Language :: Python :: 3
Requires-Dist: dill
